{
  "Summary": {
    "Label": "1a2b3c4d5e6f7890",
    "Status": "NotRun",
    "Source": {
      "Label": "Task 1a2b3c4d5e6f7890",
      "URL": "https://example.com/task?id=1a2b3c4d5e6f7890\u0026show_raw=1\u0026wide_logs=true"
    },
    "Started": "0001-01-01T00:00:00Z",
    "Finished": "0001-01-01T00:00:00Z",
    "Duration": 0,
    "Type": "Recipe",
    "LevelsDeep": 0,
    "Verbosity": 0,
    "Text": null
  },
  "SourceStamp": null,
  "Components": [
    {
      "Label": "Waiting...",
      "Status": "Running",
      "Started": "0001-01-01T00:00:00Z",
      "Finished": "0001-01-01T00:00:00Z",
      "Duration": 0,
      "Type": "Summary",
      "LevelsDeep": 0,
      "Verbosity": 0,
      "Text": [
        "waiting for annotation stream"
      ]
    }
  ],
  "PropertyGroup": null,
  "Blame": null
}